{"basic_info": {"ticker": "600745", "exchange": "XSHG", "bloomberg_ticker": "600745 CH Equity", "name": "WINGTECH TECHNOLOGY CO LTD-A", "industry": "Electronic Equipment, Instruments & Components", "name_chinese_simplified": "闻泰科技", "period": "2020", "market_value": 122128392192, "total_income": 41578163284, "ccy": "人民币元", "shariah_compliance_summary": "compliant"}, "business_activity_screening": {"summary": [{"shariah_compliance": "compliant", "income": 39786038358, "business_income_over_total_income": 0.9568974484572857}, {"shariah_compliance": "unknown", "income": 1792124924, "business_income_over_total_income": 0.0431025514946121}], "details": [{"business_activity_cn": "移动终端分项目：手机及配件", "business_activity_en": "Mobile terminal sub-items: cell phones and accessories", "income": 39786038358, "business_income_over_total_income": 0.9568974484572857, "shariah_compliance": "compliant"}, {"business_activity_cn": "其他业务", "business_activity_en": "Other business", "income": 76337057, "business_income_over_total_income": 0.001835989158024588, "shariah_compliance": "unknown"}, {"business_activity_cn": "合计特别调整", "business_activity_en": "Total special adjustments", "income": 1715787867, "business_income_over_total_income": 0.04126656233658751, "shariah_compliance": "unknown"}]}, "financial_screening": [{"item": "Debt to Market Capitalization", "amount": 0.13710945644569272, "shariah_compliance": "compliant", "amount_over_market_value": 0.13710945644569272}]}