{"basic_info": {"ticker": "601890", "exchange": "XSHG", "bloomberg_ticker": "601890 CH Equity", "name": "ASIAN STAR ANCHOR CHAIN-A", "industry": "Machinery", "name_chinese_simplified": "亚星锚链", "period": "2020", "market_value": 5842745856, "total_income": 552576720, "ccy": "人民币元", "shariah_compliance_summary": "compliant"}, "business_activity_screening": {"summary": [{"shariah_compliance": "compliant", "income": 534389544, "business_income_over_total_income": 0.9670866047342711}, {"shariah_compliance": "unknown", "income": 18187175, "business_income_over_total_income": 0.03291339345602544}], "details": [{"business_activity_cn": "系泊链", "business_activity_en": "Mooring chain", "income": 122747225, "business_income_over_total_income": 0.22213607732153465, "shariah_compliance": "compliant"}, {"business_activity_cn": "船用链", "business_activity_en": "Marine Chain", "income": 411642319, "business_income_over_total_income": 0.7449505274127365, "shariah_compliance": "compliant"}, {"business_activity_cn": "其他业务", "business_activity_en": "Other business", "income": 18187175, "business_income_over_total_income": 0.03291339345602544, "shariah_compliance": "unknown"}, {"business_activity_cn": "合计特别调整", "business_activity_en": "Total special adjustments", "income": 0, "business_income_over_total_income": 0.0, "shariah_compliance": "unknown"}]}, "financial_screening": [{"item": "Debt to Market Capitalization", "amount": 0.05287531010568802, "shariah_compliance": "compliant", "amount_over_market_value": 0.05287531010568802}]}