{"basic_info": {"ticker": "603386", "exchange": "XSHG", "bloomberg_ticker": "603386 CH Equity", "name": "GUANGDONG CHAMPION ASIA EL-A", "industry": "Electronic Equipment, Instruments & Components", "name_chinese_simplified": "广东骏亚", "period": "2020", "market_value": 3564939520, "total_income": 2065746952, "ccy": "人民币元", "shariah_compliance_summary": "non-compliant"}, "business_activity_screening": {"summary": [{"shariah_compliance": "compliant", "income": 1894461778, "business_income_over_total_income": 0.9170831771848114}, {"shariah_compliance": "unknown", "income": 171285173, "business_income_over_total_income": 0.08291682233110226}], "details": [{"business_activity_cn": "PCB", "business_activity_en": "PCB", "income": 1869307645, "business_income_over_total_income": 0.9049064035603137, "shariah_compliance": "compliant"}, {"business_activity_cn": "SMT", "business_activity_en": "SMT", "income": 92701279, "business_income_over_total_income": 0.04487542818845704, "shariah_compliance": "unknown"}, {"business_activity_cn": "整机产品", "business_activity_en": "Machine Products", "income": 25154133, "business_income_over_total_income": 0.012176773624497643, "shariah_compliance": "compliant"}, {"business_activity_cn": "其他业务", "business_activity_en": "Other business", "income": 78583894, "business_income_over_total_income": 0.038041394142645214, "shariah_compliance": "unknown"}]}, "financial_screening": [{"item": "Debt to Market Capitalization", "amount": 0.24742679918007135, "shariah_compliance": "non-compliant", "amount_over_market_value": 0.24742679918007135}]}