{"basic_info": {"ticker": "603322", "exchange": "XSHG", "bloomberg_ticker": "603322 CH Equity", "name": "SUPER TELECOM CO LTD-A", "industry": "Diversified Telecommunication Services", "name_chinese_simplified": "超讯通信", "period": "2020", "market_value": 2660839936, "total_income": 1266924953, "ccy": "人民币元", "shariah_compliance_summary": "non-compliant"}, "business_activity_screening": {"summary": [{"shariah_compliance": "compliant", "income": 1265888706, "business_income_over_total_income": 0.9991820770460424}, {"shariah_compliance": "unknown", "income": 1036242, "business_income_over_total_income": 0.0008179190073936447}], "details": [{"business_activity_cn": "通信网络维护业务", "business_activity_en": "Communication network maintenance services", "income": 486583254, "business_income_over_total_income": 0.38406635913816434, "shariah_compliance": "compliant"}, {"business_activity_cn": "通信网络建设业务", "business_activity_en": "Communication network construction business", "income": 234521988, "business_income_over_total_income": 0.18511119182289876, "shariah_compliance": "compliant"}, {"business_activity_cn": "销售业务", "business_activity_en": "Sales", "income": 21696411, "business_income_over_total_income": 0.01712525351136564, "shariah_compliance": "compliant"}, {"business_activity_cn": "以租代建业务", "business_activity_en": "Rents construction business", "income": 7040589, "business_income_over_total_income": 0.00555722656131156, "shariah_compliance": "compliant"}, {"business_activity_cn": "智慧城市", "business_activity_en": "Smart City", "income": 46699584, "business_income_over_total_income": 0.03686057638174879, "shariah_compliance": "compliant"}, {"business_activity_cn": "智慧生活", "business_activity_en": "The wisdom of life", "income": 5833144, "business_income_over_total_income": 0.004604174845706114, "shariah_compliance": "compliant"}, {"business_activity_cn": "边缘计算IDC机房收入", "business_activity_en": "Edge computing IDC room revenue", "income": 6322923, "business_income_over_total_income": 0.00499076364786068, "shariah_compliance": "compliant"}, {"business_activity_cn": "物联网公用事业综合服务", "business_activity_en": "Things utilities integrated services", "income": 300368259, "business_income_over_total_income": 0.23708449209145854, "shariah_compliance": "compliant"}, {"business_activity_cn": "物联网智慧物流综合服务", "business_activity_en": "Things wisdom of integrated logistics services", "income": 118990050, "business_income_over_total_income": 0.09392036183219765, "shariah_compliance": "compliant"}, {"business_activity_cn": "物联网节能环保综合服务", "business_activity_en": "Things comprehensive energy saving services", "income": 37832504, "business_income_over_total_income": 0.029861677213330568, "shariah_compliance": "compliant"}, {"business_activity_cn": "其他业务", "business_activity_en": "Other business", "income": 1036242, "business_income_over_total_income": 0.0008179190073936447, "shariah_compliance": "unknown"}]}, "financial_screening": [{"item": "Debt to Market Capitalization", "amount": 0.4087724116404323, "shariah_compliance": "non-compliant", "amount_over_market_value": 0.4087724116404323}]}