{"basic_info": {"ticker": "603685", "exchange": "XSHG", "bloomberg_ticker": "603685 CH Equity", "name": "ZHEJIANG CHENFENG SCIENCE -A", "industry": "Electrical Equipment", "name_chinese_simplified": "晨丰科技", "period": "2020", "market_value": 1845479936, "total_income": 447264716, "ccy": "人民币元", "shariah_compliance_summary": "non-compliant"}, "business_activity_screening": {"summary": [{"shariah_compliance": "compliant", "income": 412206095, "business_income_over_total_income": 0.9216155002935666}, {"shariah_compliance": "unknown", "income": 35058619, "business_income_over_total_income": 0.07838449523480855}], "details": [{"business_activity_cn": "灯头类", "business_activity_en": "Lamp class", "income": 123850432, "business_income_over_total_income": 0.27690633213284815, "shariah_compliance": "compliant"}, {"business_activity_cn": "LED灯泡散热器", "business_activity_en": "LED bulb heat sink", "income": 232913097, "business_income_over_total_income": 0.5207499913764716, "shariah_compliance": "compliant"}, {"business_activity_cn": "印制电路板", "business_activity_en": "Printed circuit board", "income": 51064571, "business_income_over_total_income": 0.11417080125766058, "shariah_compliance": "compliant"}, {"business_activity_cn": "灯具金属件及其他", "business_activity_en": "Lamps and other metal", "income": 4377995, "business_income_over_total_income": 0.009788375526586363, "shariah_compliance": "compliant"}, {"business_activity_cn": "其他业务", "business_activity_en": "Other business", "income": 35058619, "business_income_over_total_income": 0.07838449523480855, "shariah_compliance": "unknown"}]}, "financial_screening": [{"item": "Debt to Market Capitalization", "amount": 0.2805741807262429, "shariah_compliance": "non-compliant", "amount_over_market_value": 0.2805741807262429}]}