{"basic_info": {"ticker": "603903", "exchange": "XSHG", "bloomberg_ticker": "603903 CH Equity", "name": "CSD WATER SERVICE CO LTD -A", "industry": "Commercial Services & Supplies", "name_chinese_simplified": "中持股份", "period": "2020", "market_value": 2286032384, "total_income": 1624993819, "ccy": "人民币元", "shariah_compliance_summary": "non-compliant"}, "business_activity_screening": {"summary": [{"shariah_compliance": "compliant", "income": 1624993800, "business_income_over_total_income": 0.9999999883076478}, {"shariah_compliance": "unknown", "income": 19, "business_income_over_total_income": 1.1692352166417686e-08}], "details": [{"business_activity_cn": "环保基础设施建造服务", "business_activity_en": "Environmental infrastructure construction services", "income": 630553200, "business_income_over_total_income": 0.388034214424295, "shariah_compliance": "compliant"}, {"business_activity_cn": "运营服务", "business_activity_en": "Operations Services", "income": 427663900, "business_income_over_total_income": 0.2631787856665072, "shariah_compliance": "compliant"}, {"business_activity_cn": "技术产品销售", "business_activity_en": "Technical product sales", "income": 336992400, "business_income_over_total_income": 0.20738072727401555, "shariah_compliance": "compliant"}, {"business_activity_cn": "环境综合治理服务", "business_activity_en": "Integrated environmental management services", "income": 229784300, "business_income_over_total_income": 0.1414062609428301, "shariah_compliance": "compliant"}, {"business_activity_cn": "合计特别调整", "business_activity_en": "Total special adjustments", "income": 19, "business_income_over_total_income": 1.1692352166417686e-08, "shariah_compliance": "unknown"}]}, "financial_screening": [{"item": "Debt to Market Capitalization", "amount": 0.44974044984229244, "shariah_compliance": "non-compliant", "amount_over_market_value": 0.44974044984229244}]}