{"basic_info": {"ticker": "605118", "exchange": "XSHG", "bloomberg_ticker": "605118 CH Equity", "name": "XIAMEN LEADING OPTICS CO L-A", "industry": "Electronic Equipment, Instruments & Components", "name_chinese_simplified": "力鼎光电", "period": "2020", "market_value": 5964904960, "total_income": 465487295, "ccy": "人民币元", "shariah_compliance_summary": "compliant"}, "business_activity_screening": {"summary": [{"shariah_compliance": "compliant", "income": 465477349, "business_income_over_total_income": 0.9999786331440045}, {"shariah_compliance": "unknown", "income": 9945, "business_income_over_total_income": 2.1364707709154555e-05}], "details": [{"business_activity_cn": "镜头", "business_activity_en": "Shot", "income": 407352036, "business_income_over_total_income": 0.8751088168797388, "shariah_compliance": "compliant"}, {"business_activity_cn": "配件及其他", "business_activity_en": "Accessories and other", "income": 58125313, "business_income_over_total_income": 0.1248698162642656, "shariah_compliance": "compliant"}, {"business_activity_cn": "其他业务", "business_activity_en": "Other business", "income": 9945, "business_income_over_total_income": 2.1364707709154555e-05, "shariah_compliance": "unknown"}]}, "financial_screening": [{"item": "Debt to Market Capitalization", "amount": 0.0, "shariah_compliance": "compliant", "amount_over_market_value": 0.0}]}