{"basic_info": {"ticker": "605336", "exchange": "XSHG", "bloomberg_ticker": "605336 CH Equity", "name": "ZHEJIANG SANFER ELECTRIC C-A", "industry": "Household Durables", "name_chinese_simplified": "帅丰电器", "period": "2020", "market_value": 3921280000, "total_income": 261476730, "ccy": "人民币元", "shariah_compliance_summary": "compliant"}, "business_activity_screening": {"summary": [{"shariah_compliance": "compliant", "income": 258754267, "business_income_over_total_income": 0.9895881251077295}, {"shariah_compliance": "unknown", "income": 2722462, "business_income_over_total_income": 0.010411871067838427}], "details": [{"business_activity_cn": "集成灶", "business_activity_en": "Integrated kitchen", "income": 245651258, "business_income_over_total_income": 0.9394765568622493, "shariah_compliance": "compliant"}, {"business_activity_cn": "其他厨房用品", "business_activity_en": "Other Kitchenware", "income": 13103009, "business_income_over_total_income": 0.0501115682454802, "shariah_compliance": "compliant"}, {"business_activity_cn": "其他收入", "business_activity_en": "Other income", "income": 2722462, "business_income_over_total_income": 0.010411871067838427, "shariah_compliance": "unknown"}]}, "financial_screening": [{"item": "Debt to Market Capitalization", "amount": 0.017098144348727005, "shariah_compliance": "compliant", "amount_over_market_value": 0.017098144348727005}]}