{"basic_info": {"ticker": "900910", "exchange": "XSHG", "bloomberg_ticker": "900910 CH Equity", "name": "SHANGHAI HIGHLY GROUP CO-B", "industry": "Machinery", "name_chinese_simplified": "海立股份", "period": "2020", "market_value": 796161472, "total_income": 5022433174, "ccy": "人民币元", "shariah_compliance_summary": "non-compliant"}, "business_activity_screening": {"summary": [{"shariah_compliance": "compliant", "income": 4692746608, "business_income_over_total_income": 0.9343572020615998}, {"shariah_compliance": "unknown", "income": 329686564, "business_income_over_total_income": 0.06564279754018684}], "details": [{"business_activity_cn": "压缩机及相关制冷设备", "business_activity_en": "Refrigeration compressors and related equipment", "income": 4021919521, "business_income_over_total_income": 0.8007910472200143, "shariah_compliance": "compliant"}, {"business_activity_cn": "电机", "business_activity_en": "Motor", "income": 670827087, "business_income_over_total_income": 0.13356615484158554, "shariah_compliance": "compliant"}, {"business_activity_cn": "贸易及房产租赁", "business_activity_en": "Trade and real estate leasing", "income": 45543478, "business_income_over_total_income": 0.009068010747413879, "shariah_compliance": "unknown"}, {"business_activity_cn": "其他业务", "business_activity_en": "Other business", "income": 284143086, "business_income_over_total_income": 0.05657478679277297, "shariah_compliance": "unknown"}]}, "financial_screening": [{"item": "Debt to Market Capitalization", "amount": 1.0154332031487454, "shariah_compliance": "non-compliant", "amount_over_market_value": 1.0154332031487454}]}