{"basic_info": {"ticker": "2273", "exchange": "XSHE", "bloomberg_ticker": "002273 CH Equity", "name": "ZHEJIANG CRYSTAL-OPTECH -A", "industry": "Electronic Equipment, Instruments & Components", "name_chinese_simplified": "水晶光电", "period": "2020", "market_value": 13735524352, "total_income": 1366335603, "ccy": "人民币元", "shariah_compliance_summary": "compliant"}, "business_activity_screening": {"summary": [{"shariah_compliance": "compliant", "income": 1344079405, "business_income_over_total_income": 0.9837110312055596}, {"shariah_compliance": "unknown", "income": 22256194, "business_income_over_total_income": 0.01628896586690203}], "details": [{"business_activity_cn": "光学成像元器件", "business_activity_en": "Optical imaging Component", "income": 948029978, "business_income_over_total_income": 0.6938485507648738, "shariah_compliance": "compliant"}, {"business_activity_cn": "生物识别", "business_activity_en": "Biometrics", "income": 142529498, "business_income_over_total_income": 0.10431514606444754, "shariah_compliance": "compliant"}, {"business_activity_cn": "薄膜光学面板", "business_activity_en": "A thin film optical panel", "income": 105351862, "business_income_over_total_income": 0.07710540643798185, "shariah_compliance": "compliant"}, {"business_activity_cn": "新型显示", "business_activity_en": "The new display", "income": 21497824, "business_income_over_total_income": 0.0157339265351779, "shariah_compliance": "compliant"}, {"business_activity_cn": "蓝宝石衬底", "business_activity_en": "Sapphire substrate", "income": 33181245, "business_income_over_total_income": 0.024284842557820693, "shariah_compliance": "compliant"}, {"business_activity_cn": "反光材料", "business_activity_en": "reflective material", "income": 93488998, "business_income_over_total_income": 0.06842315884525772, "shariah_compliance": "compliant"}, {"business_activity_cn": "其他业务收入", "business_activity_en": "Other operating income", "income": 22256194, "business_income_over_total_income": 0.01628896586690203, "shariah_compliance": "unknown"}]}, "financial_screening": [{"item": "Debt to Market Capitalization", "amount": 0.01864284809552461, "shariah_compliance": "compliant", "amount_over_market_value": 0.01864284809552461}]}