{"basic_info": {"ticker": "2347", "exchange": "XSHE", "bloomberg_ticker": "002347 CH Equity", "name": "ANHUI TAIER HEAVY INDUSTRY-A", "industry": "Machinery", "name_chinese_simplified": "泰尔股份", "period": "2020", "market_value": 1944535552, "total_income": 304858982, "ccy": "人民币元", "shariah_compliance_summary": "non-compliant"}, "business_activity_screening": {"summary": [{"shariah_compliance": "compliant", "income": 302863037, "business_income_over_total_income": 0.9934528909500853}, {"shariah_compliance": "unknown", "income": 1995941, "business_income_over_total_income": 0.006547095929094193}], "details": [{"business_activity_cn": "核心备件", "business_activity_en": "The core spare parts", "income": 144885649, "business_income_over_total_income": 0.47525465068960965, "shariah_compliance": "compliant"}, {"business_activity_cn": "再制造业务", "business_activity_en": "Remanufacturing business", "income": 60673764, "business_income_over_total_income": 0.19902239258937104, "shariah_compliance": "compliant"}, {"business_activity_cn": "核心设备", "business_activity_en": "Core equipment", "income": 59270967, "business_income_over_total_income": 0.19442093065835928, "shariah_compliance": "compliant"}, {"business_activity_cn": "总包服务", "business_activity_en": "Turnkey service", "income": 20455034, "business_income_over_total_income": 0.0670967076836857, "shariah_compliance": "compliant"}, {"business_activity_cn": "成套设备", "business_activity_en": "A set of equipment", "income": 8904267, "business_income_over_total_income": 0.02920782238917271, "shariah_compliance": "compliant"}, {"business_activity_cn": "表面技术", "business_activity_en": "Surface Technology", "income": 5182649, "business_income_over_total_income": 0.017000151893179254, "shariah_compliance": "compliant"}, {"business_activity_cn": "新能源业务", "business_activity_en": "New energy business", "income": 3490707, "business_income_over_total_income": 0.011450235046707596, "shariah_compliance": "compliant"}, {"business_activity_cn": "其他", "business_activity_en": "other", "income": 1995941, "business_income_over_total_income": 0.006547095929094193, "shariah_compliance": "unknown"}, {"business_activity_cn": "合计特别调整", "business_activity_en": "Total special adjustments", "income": 0, "business_income_over_total_income": 0.0, "shariah_compliance": "unknown"}]}, "financial_screening": [{"item": "Debt to Market Capitalization", "amount": 0.2052893553340946, "shariah_compliance": "non-compliant", "amount_over_market_value": 0.2052893553340946}]}