{"basic_info": {"ticker": "2373", "exchange": "XSHE", "bloomberg_ticker": "002373 CH Equity", "name": "CHINA TRANSINFO TECHNOLOGY-A", "industry": "IT Services", "name_chinese_simplified": "千方科技", "period": "2020", "market_value": 29552316416, "total_income": 9418895592, "ccy": "人民币元", "shariah_compliance_summary": "unknown"}, "business_activity_screening": {"summary": [{"shariah_compliance": "compliant", "income": 5940074472, "business_income_over_total_income": 0.6306550926252161}, {"shariah_compliance": "unknown", "income": 3478821118, "business_income_over_total_income": 0.3693449071624447}], "details": [{"business_activity_cn": "产品销售", "business_activity_en": "Product sales", "income": 5721515998, "business_income_over_total_income": 0.6074508356223427, "shariah_compliance": "compliant"}, {"business_activity_cn": "交通行业云", "business_activity_en": "Transportation industry cloud", "income": 218558474, "business_income_over_total_income": 0.023204257002873464, "shariah_compliance": "compliant"}, {"business_activity_cn": "解决方案及增值服务", "business_activity_en": "Solutions and value-added services", "income": 3478810361, "business_income_over_total_income": 0.3693437650964886, "shariah_compliance": "unknown"}, {"business_activity_cn": "其他业务", "business_activity_en": "Other business", "income": 10757, "business_income_over_total_income": 1.1420659561335968e-06, "shariah_compliance": "unknown"}]}, "financial_screening": [{"item": "Debt to Market Capitalization", "amount": 0.03755620829944654, "shariah_compliance": "compliant", "amount_over_market_value": 0.03755620829944654}]}