{"basic_info": {"ticker": "2607", "exchange": "XSHE", "bloomberg_ticker": "002607 CH Equity", "name": "OFFCN EDUCATION TECHNOLOGY-A", "industry": "Diversified Consumer Services", "name_chinese_simplified": "中公教育", "period": "2020", "market_value": 209691574272, "total_income": 2807980480, "ccy": "人民币元", "shariah_compliance_summary": "unknown"}, "business_activity_screening": {"summary": [{"shariah_compliance": "compliant", "income": 599165612, "business_income_over_total_income": 0.2133795502737968}, {"shariah_compliance": "unknown", "income": 2208814866, "business_income_over_total_income": 0.7866204490139476}], "details": [{"business_activity_cn": "公务员序列", "business_activity_en": "Civil servants sequence", "income": 1218210409, "business_income_over_total_income": 0.43383863159903446, "shariah_compliance": "unknown"}, {"business_activity_cn": "事业单位序列", "business_activity_en": "Institutions sequence", "income": 249112502, "business_income_over_total_income": 0.08871589520451367, "shariah_compliance": "compliant"}, {"business_activity_cn": "教师序列", "business_activity_en": "Teacher sequence", "income": 350053110, "business_income_over_total_income": 0.1246636550692831, "shariah_compliance": "compliant"}, {"business_activity_cn": "综合序列", "business_activity_en": "Integrated sequence", "income": 970810977, "business_income_over_total_income": 0.34573280829929415, "shariah_compliance": "unknown"}, {"business_activity_cn": "其他", "business_activity_en": "other", "income": 19793480, "business_income_over_total_income": 0.0070490091156189235, "shariah_compliance": "unknown"}]}, "financial_screening": [{"item": "Debt to Market Capitalization", "amount": 0.033218398404998364, "shariah_compliance": "compliant", "amount_over_market_value": 0.033218398404998364}]}