{"basic_info": {"ticker": "300189", "exchange": "XSHE", "bloomberg_ticker": "300189 CH Equity", "name": "HAINAN SHENNONG TECH CO LT-A", "industry": "Food Products", "name_chinese_simplified": "神农科技", "period": "2020", "market_value": 6400000000, "total_income": 50218955, "ccy": "人民币元", "shariah_compliance_summary": "compliant"}, "business_activity_screening": {"summary": [{"shariah_compliance": "compliant", "income": 49946465, "business_income_over_total_income": 0.9945739611666551}, {"shariah_compliance": "unknown", "income": 272490, "business_income_over_total_income": 0.005426038833344899}], "details": [{"business_activity_cn": "杂交水稻种子", "business_activity_en": "Hybrid rice seeds", "income": 49655873, "business_income_over_total_income": 0.9887874608302781, "shariah_compliance": "compliant"}, {"business_activity_cn": "农化产品及其他", "business_activity_en": "And other agricultural products", "income": 290592, "business_income_over_total_income": 0.005786500336376971, "shariah_compliance": "compliant"}, {"business_activity_cn": "其他业务", "business_activity_en": "Other business", "income": 272490, "business_income_over_total_income": 0.005426038833344899, "shariah_compliance": "unknown"}]}, "financial_screening": [{"item": "Debt to Market Capitalization", "amount": 0.0037602140494791664, "shariah_compliance": "compliant", "amount_over_market_value": 0.0037602140494791664}]}