{"basic_info": {"ticker": "300425", "exchange": "XSHE", "bloomberg_ticker": "300425 CH Equity", "name": "CSCEC SCIMEE SCI & TECH CO-A", "industry": "Machinery", "name_chinese_simplified": "中建环能", "period": "2020", "market_value": 3040689664, "total_income": 387503728, "ccy": "人民币元", "shariah_compliance_summary": "non-compliant"}, "business_activity_screening": {"summary": [{"shariah_compliance": "compliant", "income": 301749680, "business_income_over_total_income": 0.778701360003432}, {"shariah_compliance": "unknown", "income": 85754046, "business_income_over_total_income": 0.22129863483532733}], "details": [{"business_activity_cn": "运营服务", "business_activity_en": "Operations Services", "income": 200125858, "business_income_over_total_income": 0.5164488585255623, "shariah_compliance": "compliant"}, {"business_activity_cn": "离心机及配套", "business_activity_en": "Centrifuges and supporting", "income": 101623822, "business_income_over_total_income": 0.26225250147786966, "shariah_compliance": "compliant"}, {"business_activity_cn": "其他业务", "business_activity_en": "Other business", "income": 2911626, "business_income_over_total_income": 0.007513801260771355, "shariah_compliance": "unknown"}, {"business_activity_cn": "合计特别调整", "business_activity_en": "Total special adjustments", "income": 82842420, "business_income_over_total_income": 0.21378483357455597, "shariah_compliance": "unknown"}]}, "financial_screening": [{"item": "Debt to Market Capitalization", "amount": 0.22552545374197738, "shariah_compliance": "non-compliant", "amount_over_market_value": 0.22552545374197738}]}