{"basic_info": {"ticker": "300666", "exchange": "XSHE", "bloomberg_ticker": "300666 CH Equity", "name": "KONFOONG MATERIALS INTERNA-A", "industry": "Semiconductors & Semiconductor Equipment", "name_chinese_simplified": "江丰电子", "period": "2020", "market_value": 10634743808, "total_income": 533105336, "ccy": "人民币元", "shariah_compliance_summary": "unknown"}, "business_activity_screening": {"summary": [{"shariah_compliance": "compliant", "income": 395315165, "business_income_over_total_income": 0.7415329359974743}, {"shariah_compliance": "unknown", "income": 137790168, "business_income_over_total_income": 0.2584670583751201}], "details": [{"business_activity_cn": "钽靶", "business_activity_en": "Tantalum target", "income": 204268241, "business_income_over_total_income": 0.3831667537463928, "shariah_compliance": "compliant"}, {"business_activity_cn": "铝靶", "business_activity_en": "Aluminum target", "income": 99108233, "business_income_over_total_income": 0.18590741136382097, "shariah_compliance": "compliant"}, {"business_activity_cn": "钛靶", "business_activity_en": "Titanium target", "income": 72033694, "business_income_over_total_income": 0.1351209397761496, "shariah_compliance": "compliant"}, {"business_activity_cn": "LCD用碳纤维支撑", "business_activity_en": "LCD carbon fiber support", "income": 19904997, "business_income_over_total_income": 0.037337831111110845, "shariah_compliance": "compliant"}, {"business_activity_cn": "其他", "business_activity_en": "other", "income": 137790168, "business_income_over_total_income": 0.2584670583751201, "shariah_compliance": "unknown"}, {"business_activity_cn": "合计特别调整", "business_activity_en": "Total special adjustments", "income": 0, "business_income_over_total_income": 0.0, "shariah_compliance": "unknown"}]}, "financial_screening": [{"item": "Debt to Market Capitalization", "amount": 0.11905799211518622, "shariah_compliance": "compliant", "amount_over_market_value": 0.11905799211518622}]}