{"basic_info": {"ticker": "300760", "exchange": "XSHE", "bloomberg_ticker": "300760 CH Equity", "name": "SHENZHEN MINDRAY BIO-MEDIC-A", "industry": "Health Care Equipment & Supplies", "name_chinese_simplified": "迈瑞医疗", "period": "2020", "market_value": 508231876608, "total_income": 10564367033, "ccy": "人民币元", "shariah_compliance_summary": "unknown"}, "business_activity_screening": {"summary": [{"shariah_compliance": "compliant", "income": 5134850903, "business_income_over_total_income": 0.4860538153360465}, {"shariah_compliance": "unknown", "income": 5429516130, "business_income_over_total_income": 0.5139461846639535}], "details": [{"business_activity_cn": "生命信息与支持类产品", "business_activity_en": "Information and life support products", "income": 5343433851, "business_income_over_total_income": 0.5057978234104014, "shariah_compliance": "unknown"}, {"business_activity_cn": "体外诊断类产品", "business_activity_en": "Vitro diagnostic products", "income": 3029703720, "business_income_over_total_income": 0.28678516285321115, "shariah_compliance": "compliant"}, {"business_activity_cn": "医学影像类产品", "business_activity_en": "Medical Imaging Products", "income": 2105147183, "business_income_over_total_income": 0.1992686524828354, "shariah_compliance": "compliant"}, {"business_activity_cn": "其他产品", "business_activity_en": "other products", "income": 62565272, "business_income_over_total_income": 0.005922292533434738, "shariah_compliance": "unknown"}, {"business_activity_cn": "其他业务", "business_activity_en": "Other business", "income": 23517007, "business_income_over_total_income": 0.0022260687201173276, "shariah_compliance": "unknown"}, {"business_activity_cn": "合计特别调整", "business_activity_en": "Total special adjustments", "income": 0, "business_income_over_total_income": 0.0, "shariah_compliance": "unknown"}]}, "financial_screening": [{"item": "Debt to Market Capitalization", "amount": 0.0, "shariah_compliance": "compliant", "amount_over_market_value": 0.0}]}