{"basic_info": {"ticker": "1626", "exchange": "XHKG", "bloomberg_ticker": "1626 HK Equity", "name": "JIA YAO HOLDINGS LTD", "industry": "Containers & Packaging", "name_chinese_simplified": "嘉耀控股", "period": "2020", "market_value": 255000000, "total_income": 576244000, "ccy": "人民币元", "shariah_compliance_summary": "non-compliant"}, "business_activity_screening": {"summary": [{"shariah_compliance": "compliant", "income": 576244000, "business_income_over_total_income": 1.0}, {"shariah_compliance": "unknown", "income": 0, "business_income_over_total_income": 0.0}], "details": [{"business_activity_cn": "纸质卷烟包装", "business_activity_en": "Cigarette packaging paper", "income": 492158000, "business_income_over_total_income": 0.8540791747940109, "shariah_compliance": "compliant"}, {"business_activity_cn": "社会产品纸质包装", "business_activity_en": "Social product paper packaging", "income": 5501000, "business_income_over_total_income": 0.009546303302073428, "shariah_compliance": "compliant"}, {"business_activity_cn": "买卖商品", "business_activity_en": "Buy and sell", "income": 78585000, "business_income_over_total_income": 0.1363745219039157, "shariah_compliance": "compliant"}, {"business_activity_cn": "未分配", "business_activity_en": "Unassigned", "income": 0, "business_income_over_total_income": 0.0, "shariah_compliance": "unknown"}]}, "financial_screening": [{"item": "Debt to Market Capitalization", "amount": 0.9025725684382706, "shariah_compliance": "non-compliant", "amount_over_market_value": 0.9025725684382706}]}