{"basic_info": {"ticker": "1708", "exchange": "XHKG", "bloomberg_ticker": "1708 HK Equity", "name": "NANJING SAMPLE TECHNOLOGY-H", "industry": "Electronic Equipment, Instruments & Components", "name_chinese_simplified": "三宝科技", "period": "2020", "market_value": 1766290432, "total_income": 945958244, "ccy": "人民币元", "shariah_compliance_summary": "non-compliant"}, "business_activity_screening": {"summary": [{"shariah_compliance": "compliant", "income": 854816329, "business_income_over_total_income": 0.9036512281825413}, {"shariah_compliance": "unknown", "income": 91141913, "business_income_over_total_income": 0.09634876970320055}], "details": [{"business_activity_cn": "系统集成", "business_activity_en": "system integration", "income": 546794375, "business_income_over_total_income": 0.5780322529754284, "shariah_compliance": "compliant"}, {"business_activity_cn": "智能终端销售", "business_activity_en": "Smart terminal sales", "income": 308021954, "business_income_over_total_income": 0.32561897520711286, "shariah_compliance": "compliant"}, {"business_activity_cn": "服务业务", "business_activity_en": "Business Services", "income": 62865030, "business_income_over_total_income": 0.06645645344151152, "shariah_compliance": "unknown"}, {"business_activity_cn": "其他业务收入", "business_activity_en": "Other operating income", "income": 28276883, "business_income_over_total_income": 0.02989231626168903, "shariah_compliance": "unknown"}, {"business_activity_cn": "未分配", "business_activity_en": "Unassigned", "income": 0, "business_income_over_total_income": 0.0, "shariah_compliance": "unknown"}]}, "financial_screening": [{"item": "Debt to Market Capitalization", "amount": 0.32878531254854, "shariah_compliance": "non-compliant", "amount_over_market_value": 0.32878531254854}]}