{"basic_info": {"ticker": "1792", "exchange": "XHKG", "bloomberg_ticker": "1792 HK Equity", "name": "CMON LTD", "industry": "Leisure Products", "name_chinese_simplified": "CMON", "period": "2020", "market_value": 133644000, "total_income": 25138861, "ccy": "美元", "shariah_compliance_summary": "non-compliant"}, "business_activity_screening": {"summary": [{"shariah_compliance": "compliant", "income": 23087475, "business_income_over_total_income": 0.9183978144435422}, {"shariah_compliance": "unknown", "income": 2051386, "business_income_over_total_income": 0.08160218555645779}], "details": [{"business_activity_cn": "产品销售", "business_activity_en": "Product sales", "income": 23087475, "business_income_over_total_income": 0.9183978144435422, "shariah_compliance": "compliant"}, {"business_activity_cn": "有关产品销售的付运收入", "business_activity_en": "For product sales revenue of days", "income": 2030264, "business_income_over_total_income": 0.08076197246963576, "shariah_compliance": "unknown"}, {"business_activity_cn": "没收收益", "business_activity_en": "Confiscation of proceeds", "income": 21122, "business_income_over_total_income": 0.0008402130868220322, "shariah_compliance": "unknown"}, {"business_activity_cn": "未分配", "business_activity_en": "Unassigned", "income": 0, "business_income_over_total_income": 0.0, "shariah_compliance": "unknown"}]}, "financial_screening": [{"item": "Debt to Market Capitalization", "amount": 0.8180513986597598, "shariah_compliance": "non-compliant", "amount_over_market_value": 0.8180513986597598}]}