{"basic_info": {"ticker": "196", "exchange": "XHKG", "bloomberg_ticker": "196 HK Equity", "name": "HONGHUA GROUP", "industry": "Energy Equipment & Services", "name_chinese_simplified": "宏华集团", "period": "2020", "market_value": 1312218752, "total_income": 3931492000, "ccy": "人民币元", "shariah_compliance_summary": "non-compliant"}, "business_activity_screening": {"summary": [{"shariah_compliance": "compliant", "income": 3931492000, "business_income_over_total_income": 1.0}, {"shariah_compliance": "unknown", "income": 0, "business_income_over_total_income": 0.0}], "details": [{"business_activity_cn": "陆地钻机", "business_activity_en": "Land rigs", "income": 621523000, "business_income_over_total_income": 0.1580883288074858, "shariah_compliance": "compliant"}, {"business_activity_cn": "零部件及其他", "business_activity_en": "Spare parts and other", "income": 1722179000, "business_income_over_total_income": 0.43804718412246546, "shariah_compliance": "compliant"}, {"business_activity_cn": "钻井工程服务", "business_activity_en": "Drilling Engineering Services", "income": 247919000, "business_income_over_total_income": 0.06305977476235484, "shariah_compliance": "compliant"}, {"business_activity_cn": "压裂业务", "business_activity_en": "Fracturing operations", "income": 1339871000, "business_income_over_total_income": 0.3408047123076939, "shariah_compliance": "compliant"}, {"business_activity_cn": "未分配", "business_activity_en": "Unassigned", "income": 0, "business_income_over_total_income": 0.0, "shariah_compliance": "unknown"}]}, "financial_screening": [{"item": "Debt to Market Capitalization", "amount": 3.6948366392813607, "shariah_compliance": "non-compliant", "amount_over_market_value": 3.6948366392813607}]}