{"basic_info": {"ticker": "2083", "exchange": "XHKG", "bloomberg_ticker": "2083 HK Equity", "name": "NATURE HOME HOLDING COMPANY", "industry": "Building Products", "name_chinese_simplified": "大自然家居", "period": "2020", "market_value": 1446673152, "total_income": 3931432000, "ccy": "人民币元", "shariah_compliance_summary": "non-compliant"}, "business_activity_screening": {"summary": [{"shariah_compliance": "compliant", "income": 3931432000, "business_income_over_total_income": 1.0}, {"shariah_compliance": "unknown", "income": 0, "business_income_over_total_income": 0.0}], "details": [{"business_activity_cn": "生产及销售地板产品", "business_activity_en": "Production and sale of flooring products", "income": 2865209000, "business_income_over_total_income": 0.7287952583180887, "shariah_compliance": "compliant"}, {"business_activity_cn": "生产及销售定制家装产品", "business_activity_en": "Custom production and sale of home improvement products", "income": 1066223000, "business_income_over_total_income": 0.27120474168191133, "shariah_compliance": "compliant"}, {"business_activity_cn": "未分配", "business_activity_en": "Unassigned", "income": 0, "business_income_over_total_income": 0.0, "shariah_compliance": "unknown"}]}, "financial_screening": [{"item": "Debt to Market Capitalization", "amount": 1.2509730025008836, "shariah_compliance": "non-compliant", "amount_over_market_value": 1.2509730025008836}]}