{"basic_info": {"ticker": "3326", "exchange": "XHKG", "bloomberg_ticker": "3326 HK Equity", "name": "PERFECT GROUP INTERNATIONAL", "industry": "Textiles, Apparel & Luxury Goods", "name_chinese_simplified": "保发集团", "period": "2020", "market_value": 298350016, "total_income": 366927000, "ccy": "港元", "shariah_compliance_summary": "compliant"}, "business_activity_screening": {"summary": [{"shariah_compliance": "compliant", "income": 366927000, "business_income_over_total_income": 1.0}, {"shariah_compliance": "unknown", "income": 0, "business_income_over_total_income": 0.0}], "details": [{"business_activity_cn": "制造及销售珠宝产品", "business_activity_en": "Manufacture and sale of jewelry products", "income": 141826000, "business_income_over_total_income": 0.38652374995571326, "shariah_compliance": "compliant"}, {"business_activity_cn": "物业业务", "business_activity_en": "Property Business", "income": 225101000, "business_income_over_total_income": 0.6134762500442867, "shariah_compliance": "compliant"}, {"business_activity_cn": "未分配", "business_activity_en": "Unassigned", "income": 0, "business_income_over_total_income": 0.0, "shariah_compliance": "unknown"}]}, "financial_screening": [{"item": "Debt to Market Capitalization", "amount": 0.016414814814814816, "shariah_compliance": "compliant", "amount_over_market_value": 0.016414814814814816}]}