{"basic_info": {"ticker": "410", "exchange": "XHKG", "bloomberg_ticker": "410 HK Equity", "name": "SOHO CHINA LTD", "industry": "Real Estate Management & Development", "name_chinese_simplified": "ＳＯＨＯ中国", "period": "2020", "market_value": 12062896128, "total_income": 2191637000, "ccy": "人民币元", "shariah_compliance_summary": "non-compliant"}, "business_activity_screening": {"summary": [{"shariah_compliance": "compliant", "income": 2191637000, "business_income_over_total_income": 1.0}, {"shariah_compliance": "unknown", "income": 0, "business_income_over_total_income": 0.0}], "details": [{"business_activity_cn": "租金收入", "business_activity_en": "rental income", "income": 1537636000, "business_income_over_total_income": 0.7015924626204065, "shariah_compliance": "compliant"}, {"business_activity_cn": "出售物业单位", "business_activity_en": "Sale of property units", "income": 654001000, "business_income_over_total_income": 0.2984075373795934, "shariah_compliance": "compliant"}, {"business_activity_cn": "未分配", "business_activity_en": "Unassigned", "income": 0, "business_income_over_total_income": 0.0, "shariah_compliance": "unknown"}]}, "financial_screening": [{"item": "Debt to Market Capitalization", "amount": 1.582356171124646, "shariah_compliance": "non-compliant", "amount_over_market_value": 1.582356171124646}]}