{"basic_info": {"ticker": "420", "exchange": "XHKG", "bloomberg_ticker": "420 HK Equity", "name": "FOUNTAIN SET HLDGS", "industry": "Textiles, Apparel & Luxury Goods", "name_chinese_simplified": "福田实业", "period": "2020", "market_value": 1114774528, "total_income": 4943230000, "ccy": "港元", "shariah_compliance_summary": "non-compliant"}, "business_activity_screening": {"summary": [{"shariah_compliance": "compliant", "income": 4943230000, "business_income_over_total_income": 1.0}, {"shariah_compliance": "unknown", "income": 0, "business_income_over_total_income": 0.0}], "details": [{"business_activity_cn": "制造及销售色布及纱", "business_activity_en": "Manufacture and sale of colored cloth and yarn", "income": 4322991000, "business_income_over_total_income": 0.8745275862138723, "shariah_compliance": "compliant"}, {"business_activity_cn": "制造及销售成衣", "business_activity_en": "Manufacture and sale of garments", "income": 620239000, "business_income_over_total_income": 0.1254724137861277, "shariah_compliance": "compliant"}, {"business_activity_cn": "未分配", "business_activity_en": "Unassigned", "income": 0, "business_income_over_total_income": 0.0, "shariah_compliance": "unknown"}]}, "financial_screening": [{"item": "Debt to Market Capitalization", "amount": 0.41485967436527743, "shariah_compliance": "non-compliant", "amount_over_market_value": 0.41485967436527743}]}