{"basic_info": {"ticker": "8367", "exchange": "XHKG", "bloomberg_ticker": "8367 HK Equity", "name": "SIMPLICITY HOLDING LTD", "industry": "Hotels, Restaurants & Leisure", "name_chinese_simplified": "倩碧控股", "period": "2020", "market_value": 142080000, "total_income": 78588000, "ccy": "港元", "shariah_compliance_summary": "non-compliant"}, "business_activity_screening": {"summary": [{"shariah_compliance": "compliant", "income": 50997000, "business_income_over_total_income": 0.6489158650175599}, {"shariah_compliance": "unknown", "income": 27591000, "business_income_over_total_income": 0.35108413498244007}], "details": [{"business_activity_cn": "中华料理", "business_activity_en": "Chinese cooking", "income": 22240000, "business_income_over_total_income": 0.28299485926604573, "shariah_compliance": "compliant"}, {"business_activity_cn": "泰国菜", "business_activity_en": "Thai", "income": 22452000, "business_income_over_total_income": 0.2856924721331501, "shariah_compliance": "unknown"}, {"business_activity_cn": "日本料理", "business_activity_en": "Japanese food", "income": 0, "business_income_over_total_income": 0.0, "shariah_compliance": "compliant"}, {"business_activity_cn": "马来西亚菜", "business_activity_en": "Malaysian cuisine", "income": 28757000, "business_income_over_total_income": 0.3659210057515142, "shariah_compliance": "compliant"}, {"business_activity_cn": "销售食材", "business_activity_en": "Food sales", "income": 5139000, "business_income_over_total_income": 0.06539166284928997, "shariah_compliance": "unknown"}, {"business_activity_cn": "未分配", "business_activity_en": "Unassigned", "income": 0, "business_income_over_total_income": 0.0, "shariah_compliance": "unknown"}]}, "financial_screening": [{"item": "Debt to Market Capitalization", "amount": 0.5818465099715099, "shariah_compliance": "non-compliant", "amount_over_market_value": 0.5818465099715099}]}