{"basic_info": {"ticker": "8371", "exchange": "XHKG", "bloomberg_ticker": "8371 HK Equity", "name": "TASTE GOURMET GROUP LTD", "industry": "Hotels, Restaurants & Leisure", "name_chinese_simplified": "尝高美集团", "period": "2020", "market_value": 499142272, "total_income": 282561000, "ccy": "港元", "shariah_compliance_summary": "non-compliant"}, "business_activity_screening": {"summary": [{"shariah_compliance": "compliant", "income": 201248000, "business_income_over_total_income": 0.7122285099500639}, {"shariah_compliance": "unknown", "income": 81314000, "business_income_over_total_income": 0.2877750291087588}], "details": [{"business_activity_cn": "越式", "business_activity_en": "Style", "income": 30004000, "business_income_over_total_income": 0.10618592091619154, "shariah_compliance": "unknown"}, {"business_activity_cn": "日式", "business_activity_en": "Japanese-style", "income": 142070000, "business_income_over_total_income": 0.5027940869405191, "shariah_compliance": "compliant"}, {"business_activity_cn": "中式", "business_activity_en": "Chinese style", "income": 45756000, "business_income_over_total_income": 0.16193317549130984, "shariah_compliance": "unknown"}, {"business_activity_cn": "西式", "business_activity_en": "Western-style", "income": 57434000, "business_income_over_total_income": 0.2032623044227618, "shariah_compliance": "compliant"}, {"business_activity_cn": "甜品", "business_activity_en": "Dessert", "income": 5554000, "business_income_over_total_income": 0.019655932701257428, "shariah_compliance": "unknown"}, {"business_activity_cn": "小食亭", "business_activity_en": "Refreshment kiosk", "income": 1744000, "business_income_over_total_income": 0.006172118586783031, "shariah_compliance": "compliant"}, {"business_activity_cn": "未分配", "business_activity_en": "Unassigned", "income": 0, "business_income_over_total_income": 0.0, "shariah_compliance": "unknown"}]}, "financial_screening": [{"item": "Debt to Market Capitalization", "amount": 0.4512946434594473, "shariah_compliance": "non-compliant", "amount_over_market_value": 0.4512946434594473}]}