{"basic_info": {"ticker": "92", "exchange": "XHKG", "bloomberg_ticker": "92 HK Equity", "name": "CHAMPION TECHNOLOGY HOLDINGS", "industry": "Oil, Gas & Consumable Fuels", "name_chinese_simplified": "冠军科技集团", "period": "2020", "market_value": 67699256, "total_income": 139593000, "ccy": "港元", "shariah_compliance_summary": "non-compliant"}, "business_activity_screening": {"summary": [{"shariah_compliance": "compliant", "income": 128142000, "business_income_over_total_income": 0.9179686660505899}, {"shariah_compliance": "non-compliant", "income": 0, "business_income_over_total_income": 0.0}, {"shariah_compliance": "unknown", "income": 11451000, "business_income_over_total_income": 0.08203133394941008}], "details": [{"business_activity_cn": "销售文化产品", "business_activity_en": "Sales of cultural products", "income": 0, "business_income_over_total_income": 0.0, "shariah_compliance": "compliant"}, {"business_activity_cn": "系统销售(包括软件特许权及服务)", "business_activity_en": "System sales (including software licensing and services)", "income": 56062000, "business_income_over_total_income": 0.401610395936759, "shariah_compliance": "compliant"}, {"business_activity_cn": "租赁系统产品", "business_activity_en": "Rental System Products", "income": 11451000, "business_income_over_total_income": 0.08203133394941008, "shariah_compliance": "unknown"}, {"business_activity_cn": "可再生能源", "business_activity_en": "Renewable Energy", "income": 4234000, "business_income_over_total_income": 0.030331033791092678, "shariah_compliance": "compliant"}, {"business_activity_cn": "策略性投资", "business_activity_en": "Strategic Investment", "income": 0, "business_income_over_total_income": 0.0, "shariah_compliance": "non-compliant"}, {"business_activity_cn": "成品油及其他的贸易", "business_activity_en": "Refined oil and other trade", "income": 65446000, "business_income_over_total_income": 0.46883439714025776, "shariah_compliance": "compliant"}, {"business_activity_cn": "船运业务", "business_activity_en": "Shipping business", "income": 2400000, "business_income_over_total_income": 0.017192839182480497, "shariah_compliance": "compliant"}, {"business_activity_cn": "未分配", "business_activity_en": "Unassigned", "income": 0, "business_income_over_total_income": 0.0, "shariah_compliance": "unknown"}]}, "financial_screening": [{"item": "Debt to Market Capitalization", "amount": 3.777988609603022, "shariah_compliance": "non-compliant", "amount_over_market_value": 3.777988609603022}]}